flet_webview/__init__.py
flet_webview/types.py
flet_webview/webview.py
flet_webview-0.80.5.dist-info/licenses/LICENSE
flutter/flet_webview/analysis_options.yaml
flutter/flet_webview/pubspec.lock
flutter/flet_webview/pubspec.yaml
flutter/flet_webview/lib/flet_webview.dart
flutter/flet_webview/lib/src/extension.dart
flutter/flet_webview/lib/src/webview.dart
flutter/flet_webview/lib/src/webview_mobile_and_mac.dart
flutter/flet_webview/lib/src/webview_web.dart
flutter/flet_webview/lib/src/webview_web_vain.dart
flutter/flet_webview/lib/src/webview_windows_and_linux.dart
flutter/flet_webview/lib/src/webview_windows_and_linux_vain.dart
flutter/flet_webview/lib/src/utils/webview.dart
flet_webview-0.80.5.dist-info/METADATA
flet_webview-0.80.5.dist-info/WHEEL
flet_webview-0.80.5.dist-info/top_level.txt
flet_webview-0.80.5.dist-info/RECORD
